icees/__init__.py
icees/iceesclient.py
icees_client-0.0.3.dist-info/METADATA
icees_client-0.0.3.dist-info/WHEEL
icees_client-0.0.3.dist-info/top_level.txt
icees_client-0.0.3.dist-info/RECORD
